setup.py
SFLF2T.egg-info/PKG-INFO
SFLF2T.egg-info/SOURCES.txt
SFLF2T.egg-info/dependency_links.txt
SFLF2T.egg-info/entry_points.txt
SFLF2T.egg-info/not-zip-safe
SFLF2T.egg-info/requires.txt
SFLF2T.egg-info/top_level.txt
sflf2t/__init__.py
sflf2t/config.py
sflf2t/core.py
sflf2t/example_plugin.py
sflf2t/git.py
sflf2t/hamster.py
sflf2t/imapfetch.py
sflf2t/private.py
sflf2t/redmine.py
sflf2t/zimbra.py
sflf2t/old/__init__.py
sflf2t/old/f2tsearchparser.py
sflf2t/old/hamster.py
sflf2t/old/private_automator.py
sflf2t/old/rmsearcher.py