Metadata-Version: 1.1
Name: SFLF2T
Version: 0.1
Summary: SFL - Outil de gestion des feuilles de temps - Private
Home-page: UNKNOWN
Author: Alexandre Bourget
Author-email: alexandre.bourget@savoirfairelinux.com
License: UNKNOWN
Keywords: web sfl private
Platform: UNKNOWN
Classifier: Programming Language :: Python
Classifier: Topic :: Internet :: WWW/HTTP
